analyzer/__init__.py
analyzer/main.py
analyzer/models/__init__.py
analyzer/models/dependency.py
analyzer/models/schemas.py
analyzer/services/__init__.py
analyzer/services/dependency_extractor.py
analyzer/services/package_info.py
analyzer/services/repo_health.py
analyzer/utils/__init__.py
analyzer/utils/helpers.py
extractor/__init__.py
extractor/cli.py
extractor/models.py
extractor/utils.py
extractor/extractor/__init__.py
extractor/extractor/environment_yml.py
extractor/extractor/package_json.py
extractor/extractor/poetry_lock.py
extractor/extractor/pyproject_toml.py
extractor/extractor/requirements_txt.py
vitalis-0.1.0.dist-info/licenses/LICENSE
vitalis-0.1.0.dist-info/METADATA
vitalis-0.1.0.dist-info/WHEEL
vitalis-0.1.0.dist-info/entry_points.txt
vitalis-0.1.0.dist-info/top_level.txt
vitalis-0.1.0.dist-info/RECORD
