Metadata-Version: 2.4
Name: vitalis
Version: 0.1.0
Summary: A CLI tool for extracting and analyzing dependency manifests across multiple ecosystems
Author: Vitalis Team
License-Expression: Apache-2.0
Project-URL: Homepage, https://github.com/zchryr/vitalis
Project-URL: Bug Reports, https://github.com/zchryr/vitalis/issues
Project-URL: Source, https://github.com/zchryr/vitalis
Classifier: Development Status :: 3 - Alpha
Classifier: Intended Audience :: Developers
Classifier: Programming Language :: Python :: 3
Classifier: Programming Language :: Python :: 3.9
Classifier: Programming Language :: Python :: 3.10
Classifier: Programming Language :: Python :: 3.11
Classifier: Programming Language :: Python :: 3.12
Requires-Python: >=3.8
License-File: LICENSE
Requires-Dist: typer>=0.9.0
Requires-Dist: pyyaml>=6.0
Requires-Dist: toml>=0.10.2
Provides-Extra: dev
Requires-Dist: pytest>=7.0.0; extra == "dev"
Requires-Dist: build>=0.10.0; extra == "dev"
Requires-Dist: twine>=4.0.0; extra == "dev"
Dynamic: license-file
